Workbook

Sheet Peer_Data
A1: Indian listed hospital chains - FY26 (year ended 31 Mar 2026) benchmark
A2: Blue = hard-coded from public company disclosures (see Source column). N/D = not disclosed / not found; deliberately left blank, not estimated.
A4: Chain | B4: ARPOB (Rs/day) | C4: Occupancy | D4: EBITDA margin (hospital) | E4: ALOS (days) | F4: Revenue (Rs Cr) | G4: Margin basis / notes | H4: Source
A5: Max Healthcare | B5: 77800 | C5: 0.76 | D5: 0.262 | E5: 4.1 | F5: 10538 | G5: Network gross revenue; operating EBITDA margin 26.2%. ARPOB = approx. average of 4 quarterly figures (78.0k, 77.3k, 77.9k, 77.9k). ALOS ~4.0-4.2 by quarter. | H5: Max Healthcare Q4 FY26 investor release to NSE, 21 May 2026; earnings call 29 May 2026
A6: Fortis Healthcare | B6: =2.51*10000000/365 -> 68767.123 | C6: 0.68 | D6: 0.222 | F6: 7773 | G6: Hospital business only. ARPOB reported as Rs 2.51 Cr per annum per bed; converted to per-day in col B by formula. ALOS N/D for FY26. | H6: Fortis Q4 FY26 press release, 22 May 2026
A7: Medanta (Global Health) | B7: 66550 | C7: 0.62 | D7: 0.242 | F7: 4509 | G7: EBITDA incl. new Noida hospital 24.2% (25.7% ex-Noida). Revenue = total income. ALOS Q3 FY26 was 3.02 days (single quarter, not FY). | H7: Global Health Q4 FY26 results (via Medical Buyer summary of company release); Q3 FY26 call
A8: KIMS | B8: 44644 | C8: 0.505 | D8: 0.211 | E8: 3.57 | F8: 3931 | G8: Standalone total revenue Rs 3,931 Cr. Mature units earn ~29.5-30% margin; new Maharashtra/Karnataka units dilute group margin. | H8: KIMS Q4 FY26 press release (16 May 2026); FY26 results summary
A9: Apollo Hospitals (Healthcare Services) | C9: 0.68 | D9: 0.244 | F9: 12555 | G9: Segment margin 24.4%. Occupancy is Q4 FY26 group-wide (68%). ARPOB N/D: Apollo reports ARPP (revenue per patient), which is a different metric. | H9: Apollo Q4 FY26 earnings summary / call transcript, May 2026
A10: Narayana Health (India hospitals) | D10: 0.231 | G10: India hospital EBITDA margin 23.1%. Management says it does not report occupancy (indicates ~60-65%) and prefers ARPIP. Q4 FY26 ALOS 4.4 days. | H10: Narayana Q4 FY26 call and results summary, May 2026
A12: Peer medians (chains with full data) | B12: =MEDIAN(B5:B10) -> 67658.562 | C12: =MEDIAN(C5:C10) -> 0.68 | D12: =MEDIAN(D5:D10) -> 0.2365 | E12: =MEDIAN(E5:E10) -> 3.835
A14: Cautions: (1) margin definitions differ (network vs hospital-only vs consolidated, pre/post Ind AS 116); (2) Medanta/KIMS/Apollo margins are diluted by new-hospital ramp-up; (3) ARPOB is not directly comparable across chains with different case mix and geography.

Sheet Driver_Analysis
A1: Why do revenues per bed differ? Revenue per available bed = ARPOB x occupancy x 365
A3: Chain | B3: ARPOB (Rs/day) | C3: Occupancy | D3: Revenue per available bed (Rs lakh/yr) | E3: Index vs KIMS (=100) | F3: Gap vs Max (Rs lakh) | G3: ...of which price (ARPOB) effect | H3: ...of which occupancy effect
A4: Max Healthcare | B4: =Peer_Data!B5 -> 77800 | C4: =Peer_Data!C5 -> 0.76 | D4: =B4*C4*365/100000 -> 215.8172 | E4: =D4/$D$7*100 -> 262.26402 | F4: =D4-$D$4 -> 0 | G4: =(B4-$B$4)*$C$4*365/100000 -> 0 | H4: =(C4-$C$4)*B4*365/100000 -> 0
A5: Fortis Healthcare | B5: =Peer_Data!B6 -> 68767.123 | C5: =Peer_Data!C6 -> 0.68 | D5: =B5*C5*365/100000 -> 170.68 | E5: =D5/$D$7*100 -> 207.41267 | F5: =D5-$D$4 -> -45.1372 | G5: =(B5-$B$4)*$C$4*365/100000 -> -25.0572 | H5: =(C5-$C$4)*B5*365/100000 -> -20.08
A6: Medanta (Global Health) | B6: =Peer_Data!B7 -> 66550 | C6: =Peer_Data!C7 -> 0.62 | D6: =B6*C6*365/100000 -> 150.60265 | E6: =D6/$D$7*100 -> 183.0144 | F6: =D6-$D$4 -> -65.21455 | G6: =(B6-$B$4)*$C$4*365/100000 -> -31.2075 | H6: =(C6-$C$4)*B6*365/100000 -> -34.00705
A7: KIMS | B7: =Peer_Data!B8 -> 44644 | C7: =Peer_Data!C8 -> 0.505 | D7: =B7*C7*365/100000 -> 82.290053 | E7: =D7/$D$7*100 -> 100 | F7: =D7-$D$4 -> -133.52715 | G7: =(B7-$B$4)*$C$4*365/100000 -> -91.974744 | H7: =(C7-$C$4)*B7*365/100000 -> -41.552403
A9: Method: Gap vs Max = price effect + occupancy effect. Price effect = (ARPOB_chain - ARPOB_Max) x Max occupancy x 365. Occupancy effect = (Occ_chain - Occ_Max) x ARPOB_chain x 365. The two sum exactly to the gap. Only chains with both ARPOB and occupancy disclosed are included.
A11: Check: price + occupancy effect - gap (should be 0) | F11: =SUMPRODUCT(G5:G7+H5:H7-F5:F7) -> 0

Sheet Lever_Model
A1: Illustrative mid-sized chain: how much EBITDA do occupancy and length-of-stay levers add?
A2: HYPOTHETICAL chain, not a real company. Blue cells are assumptions you can change (yellow = key assumptions). Base values set near the lower half of the peer range.
A4: Operational beds | B4: 2000 | C4: Assumption: a mid-sized chain (peers range ~3,000-5,000+ beds).
A5: Base occupancy | B5: 0.6 | C5: Assumption: between KIMS (50.5%) and peer median.
A6: Base ARPOB (Rs/day) | B6: 55000 | C6: Assumption: between KIMS (44,644) and Medanta/Fortis (~67-69k).
A7: Base EBITDA margin | B7: 0.2 | C7: Assumption: within observed 21-26% peer range, slightly below.
A8: Contribution margin on incremental revenue | B8: 0.45 | C8: KEY ASSUMPTION: share of each extra rupee of revenue that drops to EBITDA (the rest is variable cost: consumables, doctor fees, etc.). Not publicly disclosed; tested in sensitivity below.
A9: Base ALOS (days) | B9: 4 | C9: Assumption: peers range 3.57 (KIMS) to ~4.1 (Max).
A10: Occupancy lever (percentage points) | B10: 0.05 | C10: Scenario lever.
A11: ALOS reduction (days) | B11: 0.5 | C11: Scenario lever.
A12: ARPOB uplift per 1% ALOS reduction | B12: 0.5 | C12: KEY ASSUMPTION: shorter stays raise revenue per bed-day because expensive days (surgery, ICU) are front-loaded. Medanta Q3 FY26: ALOS -6.6% with ARPOB +9.9% (but case mix also changed), so 0.5 is deliberately conservative.
A14: BASE CASE
A15: Revenue (Rs Cr) | B15: =B4*B5*365*B6/10000000 -> 2409
A16: EBITDA (Rs Cr) | B16: =B15*B7 -> 481.8
A17: Fixed-cost-equivalent (Rs Cr) = Revenue x Contribution margin - EBITDA | B17: =B15*B8-B16 -> 602.25
A19: SCENARIOS
A20: Scenario | B20: Revenue (Rs Cr) | C20: EBITDA (Rs Cr) | D20: EBITDA change (Rs Cr) | E20: EBITDA change % | F20: New EBITDA margin
A21: 1. Occupancy +5 pts (price & ALOS unchanged) | B21: =B4*(B5+B10)*365*B6/10000000 -> 2609.75 | C21: =$B$16+(B21-$B$15)*$B$8 -> 572.1375 | D21: =C21-$B$16 -> 90.3375 | E21: =D21/$B$16 -> 0.1875 | F21: =C21/B21 -> 0.21923077
A22: 2. ALOS -0.5 day (freed beds refilled; ARPOB rises) | B22: =B4*B5*365*B6*(1+B12*(B11/B9))/10000000 -> 2559.5625 | C22: =$B$16+(B22-$B$15)*$B$8 -> 549.55313 | D22: =C22-$B$16 -> 67.753125 | E22: =D22/$B$16 -> 0.140625 | F22: =C22/B22 -> 0.21470588
A23: 3. Both levers together | B23: =B4*(B5+B10)*365*B6*(1+B12*(B11/B9))/10000000 -> 2772.8594 | C23: =$B$16+(B23-$B$15)*$B$8 -> 645.53672 | D23: =C23-$B$16 -> 163.73672 | E23: =D23/$B$16 -> 0.33984375 | F23: =C23/B23 -> 0.23280543
A24: Note: scenario 2 assumes demand exists to refill freed beds (otherwise occupancy falls). Scenario 3 is a simple product, not additive.
A26: SENSITIVITY: EBITDA gain (Rs Cr) from +5 pt occupancy, by contribution margin and base ARPOB
A27: Contribution margin -> | B27: 0.35 | C27: 0.45 | D27: 0.55
A28: 45000 | B28: =$B$4*$B$10*365*$A28/10000000*B$27 -> 57.4875 | C28: =$B$4*$B$10*365*$A28/10000000*C$27 -> 73.9125 | D28: =$B$4*$B$10*365*$A28/10000000*D$27 -> 90.3375
A29: 55000 | B29: =$B$4*$B$10*365*$A29/10000000*B$27 -> 70.2625 | C29: =$B$4*$B$10*365*$A29/10000000*C$27 -> 90.3375 | D29: =$B$4*$B$10*365*$A29/10000000*D$27 -> 110.4125
A30: 65000 | B30: =$B$4*$B$10*365*$A30/10000000*B$27 -> 83.0375 | C30: =$B$4*$B$10*365*$A30/10000000*C$27 -> 106.7625 | D30: =$B$4*$B$10*365*$A30/10000000*D$27 -> 130.4875
